Workbook

Sheet Read Me First
A1: MedfirstIndia (MFI) — Simulated Digital Marketing Analytics Dataset
A2: Prepared for BUSB7052: The Marketing Challenge — Assessment 2 (Individual Consultancy Report)
A4: WHAT THIS FILE IS
A5: This workbook is a fully simulated dataset.
A6: WHY IT LOOKS THE WAY IT DOES
A7: The structure (sheet names, column headers) mirrors a typical e-commerce Google Analytics export, so the dataset is usable in the same way the case describes MFI's own dashboard being used. The figures themselves have been built to be internally consistent and to reflect the qualitative narrative in the case — for example: Paid Search and Facebook (Social) absorbing the large majority of the advertising budget while converting poorly; Organic Search, Direct and Referral traffic converting disproportionately well despite little or no paid spend; revenue concentrated in a handful of Tier 1 cities; a core buyer base of doctors aged roughly 35-54; and visible data-quality problems (duplicated categories, unlabelled rows, figures that do not perfectly reconcile between tabs) consistent with the case's account of broken Google Analytics tracking.
A8: HOW TO USE IT
A9: Treat this as you would treat a real but imperfect analytics export handed to you by a client. You are not expected to use every sheet - the assessment brief asks you to select what is relevant to your chosen consultancy pathway (e.g., channel performance, segmentation, conversion optimisation, analytics governance). Where you notice inconsistencies or gaps, that is a deliberate and legitimate feature of the dataset, not an error to be corrected - the assessment brief explicitly invites you to flag data quality issues as part of your analysis.
A11: REPORTING PERIOD
A12: 1 September 2015 to 31 August 2018 - the approximate three years of MFI's digital marketing operation referenced by Karpuram in the case ("three years of running MFI's marketing operations"). All monetary values are in Indian Rupees (Rs).
A13: CONTENTS
A14: 1. Channel Performance - traffic and revenue by marketing channel, with 3-year ad spend by channel
... A23: 10. KPI Reference Sheet - generic marketing KPI definitions you may draw on for your measurement framework

Sheet Channel Performance
A1: Default Channel Grouping | B1: New Users | C1: Sessions | D1: Bounce Rate | E1: Pages per Session | F1: Average Session Duration (sec) | G1: E-Commerce Conversion Rate | H1: Transactions | I1: Revenue (Rs) | J1: 3-Year Ad Spend (Rs)
A2: Organic search | B2: 142300 | C2: 178540 | D2: 0.158 | E2: 4.1 | F2: 132 | G2: 0.0042 | H2: 750 | I2: 3270900 | J2: 0
A3: Direct | B3: 51200 | C3: 63880 | D3: 0.214 | E3: 4.4 | F3: 165 | G3: 0.0058 | H3: 371 | I3: 1704600 | J3: 0
A4: Referral | B4: 9850 | C4: 13760 | D4: 0.241 | E4: 5.2 | F4: 189 | G4: 0.029 | H4: 399 | I4: 2318500 | J4: 0
A5: Paid search | B5: 39700 | C5: 48330 | D5: 0.139 | E5: 4.5 | F5: 128 | G5: 0.0031 | H5: 150 | I5: 612300 | J5: 3600000
A6: Social | B6: 46900 | C6: 58120 | D6: 0.276 | E6: 3.6 | F6: 96 | G6: 0.0022 | H6: 128 | I6: 501800 | J6: 3000000
A7: Email | B7: 620 | C7: 1140 | D7: 0.092 | E7: 8.7 | F7: 340 | G7: 0.011 | H7: 13 | I7: 71200 | J7: 600000
A8: Total | B8: =SUM(B2:B7) -> 290570 | C8: =SUM(C2:C7) -> 363770 | H8: =SUM(H2:H7) -> 1811 | I8: =SUM(I2:I7) -> 8479300 | J8: =SUM(J2:J7) -> 7200000
A10: Note: 'Ad Spend' is media/working spend only. It excludes the agency's fixed monthly retainer of Rs 100,000 (Rs 3,600,000 over 3 years), which covered SEO, organic content and overall account management and is not attributed to a single channel here - consistent with how the case describes the agency's fee structure.

Sheet Source Data
A1: Source | B1: Users | C1: New Users | D1: Sessions | E1: Bounce Rate | F1: Pages / Session | G1: Avg. Session Duration (sec) | H1: E-Commerce Conversion Rate | I1: Transactions | J1: Revenue (Rs)
A2: google (organic) | B2: 98400 | C2: 91100 | D2: 122600 | E2: 0.152 | F2: 4.2 | G2: 135 | H2: 0.0044 | I2: 543 | J2: 2412100
A3: (direct) | B3: 44300 | C3: 51200 | D3: 63880 | E3: 0.214 | F3: 4.4 | G3: 165 | H3: 0.0058 | I3: 371 | J3: 1704600
A4: bing (organic) | B4: 12100 | C4: 11200 | D4: 15340 | E4: 0.201 | F4: 3.9 | G4: 118 | H4: 0.0028 | I4: 43 | J4: 188900
A5: google / cpc | B5: 28900 | C5: 26100 | D5: 33400 | E5: 0.131 | F5: 4.6 | G5: 131 | H5: 0.0035 | I5: 117 | J5: 478200
A6: google / display | B6: 9800 | C6: 9100 | D6: 11200 | E6: 0.332 | F6: 2.2 | G6: 48 | H6: 0.0009 | I6: 10 | J6: 38900
A7: m.facebook.com / cpc | B7: 31200 | C7: 29800 | D7: 37600 | E7: 0.289 | F7: 3.4 | G7: 91 | H7: 0.0019 | I7: 71 | J7: 278900
A8: facebook / cpc | B8: 10300 | C8: 9600 | D8: 12100 | E8: 0.254 | F8: 3.9 | G8: 104 | H8: 0.0028 | I8: 34 | J8: 148100
A9: instagram / cpc | B9: 5900 | C9: 5500 | D9: 6900 | E9: 0.361 | F9: 3.1 | G9: 77 | H9: 0.0013 | I9: 9 | J9: 38700
A10: youtube.com | B10: 2100 | C10: 1900 | D10: 2600 | E10: 0.226 | F10: 4.6 | G10: 143 | H10: 0.0031 | I10: 8 | J10: 31200
A11: practomed.in | B11: 680 | C11: 610 | D11: 910 | E11: 0.198 | F11: 5.8 | G11: 201 | H11: 0.033 | I11: 30 | J11: 173900
A12: medibuyerindia.com | B12: 540 | C12: 490 | D12: 720 | E12: 0.215 | F12: 5.3 | G12: 188 | H12: 0.029 | I12: 21 | J12: 118400
A13: hospitalsourcing.co.in | B13: 410 | C13: 370 | D13: 560 | E13: 0.244 | F13: 4.9 | G13: 175 | H13: 0.025 | I13: 14 | J13: 79300
... A21: referral / (not set) | B21: 1900 | C21: 1700 | D21: 2650 | E21: 0.305 | F21: 3.3 | G21: 95 | H21: 0.0068 | I21: 18 | J21: 85200
A22: Total (approx.) | B22: =SUM(B2:B21) -> 270260 | C22: =SUM(C2:C21) -> 260700 | D22: =SUM(D2:D21) -> 339510 | I22: =SUM(I2:I21) -> 1435 | J22: =SUM(J2:J21) -> 6478700
A24: Note: Source-level totals will not tie back exactly to the Channel Performance tab. This reflects the case's account of incomplete GA-to-website integration (some product pages and campaigns were not properly linked to revenue tracking). Treat the mismatch as a data-quality finding, not an error to reconcile.

Sheet Top Assisted Conversion Paths
A1: Channel Grouping Path | B1: Conversions | C1: Conversion Value (Rs)
A2: Organic search > Direct | B2: 212 | C2: 1084300
A3: Organic search > Referral | B3: 96 | C3: 612800
A4: Direct > Direct | B4: 158 | C4: 498100
A5: Organic search > Direct > Direct | B5: 74 | C5: 201900
A6: Referral > Direct | B6: 61 | C6: 318400
A7: Paid search > Direct | B7: 58 | C7: 142300
A8: Organic search > Paid search > Direct | B8: 41 | C8: 109800
A9: Social > Direct | B9: 37 | C9: 68900
A10: Direct > Organic search | B10: 33 | C10: 101200
A11: Organic search > Social > Direct | B11: 29 | C11: 61400
A12: Referral > Referral | B12: 24 | C12: 188900
A13: Paid search > Paid search > Direct | B13: 19 | C13: 38900
... A16: Paid search > Organic search > Direct | B16: 9 | C16: 28400
A17: Total | B17: =SUM(B2:B16) -> 876 | C17: =SUM(C2:C16) -> 3536300

Sheet Customer Demographics
A1: Age | B1: Users | C1: New Users | D1: Sessions | E1: Bounce Rate | F1: Pages per Session | G1: Average Session Duration (sec) | H1: Transactions | I1: Revenue (Rs) | J1: E-Commerce Conversion Rate
A2: 18-24 | B2: 12100 | C2: 11400 | D2: 15800 | E2: 0.296 | F2: 3.1 | G2: 88 | H2: 22 | I2: 79400 | J2: 0.0014
A3: 25-34 | B3: 41200 | C3: 37600 | D3: 51900 | E3: 0.201 | F3: 3.9 | G3: 118 | H3: 214 | I3: 842100 | J3: 0.0041
A4: 35-44 | B4: 68900 | C4: 61300 | D4: 84600 | E4: 0.142 | F4: 4.8 | G4: 168 | H4: 611 | I4: 2988700 | J4: 0.0072
A5: 45-54 | B5: 52700 | C5: 46100 | D5: 63200 | E5: 0.155 | F5: 4.6 | G5: 159 | H5: 448 | I5: 2211900 | J5: 0.0071
A6: 55-64 | B6: 18400 | C6: 16200 | D6: 22300 | E6: 0.178 | F6: 4.2 | G6: 141 | H6: 121 | I6: 598400 | J6: 0.0054
A7: 65+ | B7: 6200 | C7: 5500 | D7: 7600 | E7: 0.199 | F7: 3.7 | G7: 122 | H7: 33 | I7: 158700 | J7: 0.0043
A8: Total | B8: =SUM(B2:B7) -> 199500 | C8: =SUM(C2:C7) -> 178100 | D8: =SUM(D2:D7) -> 245400 | H8: =SUM(H2:H7) -> 1449 | I8: =SUM(I2:I7) -> 6879200
A10: Note: Because MFI is a B2B platform ordered through a shared clinic or hospital login, 'Age' reflects the self-reported age of the individual placing the order (typically the doctor or practice owner) rather than a patient or end consumer, consistent with the case's description of MFI's core buyers as doctor-owners of independent practices and polyclinics.

Sheet Regional Analysis
A1: Region | B1: Users | C1: New Users | D1: Sessions | E1: Bounce Rate | F1: Pages per Session | G1: Average Session Duration (sec) | H1: Transactions | I1: Revenue (Rs) | J1: E-Commerce Conversion Rate
A2: North | B2: 44200 | C2: 39800 | D2: 55100 | E2: 0.168 | F2: 4.3 | G2: 148 | H2: 298 | I2: 1489200 | J2: 0.0054
A3: South | B3: 61300 | C3: 54900 | D3: 76200 | E3: 0.149 | F3: 4.7 | G3: 162 | H3: 501 | I3: 2601800 | J3: 0.0066
A4: West | B4: 38900 | C4: 34600 | D4: 48300 | E4: 0.177 | F4: 4.1 | G4: 139 | H4: 241 | I4: 1198700 | J4: 0.005
A5: East | B5: 9600 | C5: 8500 | D5: 11900 | E5: 0.221 | F5: 3.6 | G5: 112 | H5: 38 | I5: 168900 | J5: 0.0032
A6: East | B6: 1200 | C6: 1050 | D6: 1600 | E6: 0.254 | F6: 3.2 | G6: 98 | H6: 4 | I6: 19800 | J6: 0.0025
A7: Central | B7: 6800 | C7: 6000 | D7: 8400 | E7: 0.199 | F7: 3.9 | G7: 121 | H7: 31 | I7: 142300 | J7: 0.0037
A8: Northeast | B8: 1400 | C8: 1250 | D8: 1800 | E8: 0.263 | F8: 3.1 | G8: 89 | H8: 3 | I8: 12900 | J8: 0.0017
A9: (not set) | B9: 3700 | C9: 3200 | D9: 4600 | E9: 0.312 | F9: 2.7 | G9: 74 | H9: 11 | I9: 48900 | J9: 0.0024
A10: (not set) | B10: 410 | C10: 360 | D10: 540 | E10: 0.345 | F10: 2.4 | G10: 66 | H10: 1 | I10: 4100 | J10: 0.0019
A11: Total | B11: =SUM(B2:B10) -> 167510 | C11: =SUM(C2:C10) -> 149660 | D11: =SUM(D2:D10) -> 208440 | H11: =SUM(H2:H10) -> 1128 | I11: =SUM(I2:I10) -> 5686600
A13: Note: 'East' and '(not set)' each appear as two separate rows rather than one. This is not a typo to be corrected before analysis - it mirrors the case's account of a Google Analytics set-up with integration mistakes, and is itself relevant evidence for a pathway focused on analytics governance and data quality.

Sheet City Performance
A1: Country | B1: City | C1: New Users | D1: Sessions | E1: Bounce Rate | F1: Pages per Session | G1: Average Session Duration (sec) | H1: Transactions | I1: Revenue (Rs) | J1: E-Commerce Conversion Rate
A2: India | B2: New Delhi | C2: 19821 | D2: 25573 | E2: 0.1901 | F2: 4.98 | G2: 131 | H2: 227 | I2: 1713626.3 | J2: 0.0089
A3: India | B3: Bengaluru | C3: 16530 | D3: 22034 | E3: 0.1615 | F3: 4.52 | G3: 185 | H3: 158 | I3: 1235583.9 | J3: 0.0072
A4: India | B4: Mumbai | C4: 13613 | D4: 17956 | E4: 0.1688 | F4: 4.09 | G4: 178 | H4: 129 | I4: 972090.6 | J4: 0.0072
A5: India | B5: Hyderabad | C5: 12444 | D5: 15220 | E5: 0.1925 | F5: 5.09 | G5: 137 | H5: 95 | I5: 417309.97 | J5: 0.0063
A6: India | B6: Chennai | C6: 10060 | D6: 12660 | E6: 0.1821 | F6: 5.35 | G6: 146 | H6: 74 | I6: 463687.37 | J6: 0.0059
A7: India | B7: Pune | C7: 8218 | D7: 10952 | E7: 0.1633 | F7: 4.32 | G7: 168 | H7: 67 | I7: 526873.53 | J7: 0.0062
A8: India | B8: Kolkata | C8: 7825 | D8: 10229 | E8: 0.1883 | F8: 5.13 | G8: 150 | H8: 55 | I8: 396163.91 | J8: 0.0054
A9: India | B9: Ahmedabad | C9: 6072 | D9: 8032 | E9: 0.1305 | F9: 5.1 | G9: 168 | H9: 60 | I9: 458112.46 | J9: 0.0075
A10: India | B10: Jaipur | C10: 2644 | D10: 3160 | E10: 0.184 | F10: 3.36 | G10: 131 | H10: 10 | I10: 57218.03 | J10: 0.0034
A11: India | B11: Lucknow | C11: 2621 | D11: 3108 | E11: 0.2254 | F11: 3.98 | G11: 111 | H11: 6 | I11: 31709.03 | J11: 0.0021
A12: India | B12: Chandigarh | C12: 1945 | D12: 2370 | E12: 0.2553 | F12: 3.53 | G12: 98 | H12: 6 | I12: 28789.31 | J12: 0.0028
A13: India | B13: Nagpur | C13: 2044 | D13: 2446 | E13: 0.2484 | F13: 4.13 | G13: 117 | H13: 10 | I13: 43677.08 | J13: 0.0044
... A41: India | B41: Siliguri | C41: 246 | D41: 273 | E41: 0.283 | F41: 2.85 | G41: 90 | H41: 0 | I41: 0 | J41: 0.0023
A42: Total | C42: =SUM(C2:C41) -> 121840 | D42: =SUM(D2:D41) -> 155145 | H42: =SUM(H2:H41) -> 953 | I42: =SUM(I2:I41) -> 6629973
A44: Note: The top 8 (Tier 1) cities account for the large majority of sessions and revenue, consistent with the case's observation that 'the bulk of the business came from four or five Tier 1 cities' rather than the smaller towns the founders originally expected to be under-served and therefore most receptive.

Sheet Product Performance
A1: Rank | B1: Product | C1: Category | D1: Product Revenue (Rs) | E1: Unique Purchases | F1: Quantity | G1: Average Price (Rs) | H1: Average Quantity per Purchase | I1: Product Refund Amount (Rs) | J1: Cart-to-Detail Rate | K1: Buy-to-Detail Rate
A2: 1 | B2: Infusion Pump - VitalTrack Volumetric | C2: Medical Equipment | D2: 350835.6 | E2: 6 | F2: 8 | G2: 43854.45 | H2: 1.33 | I2: 7016.71 | J2: 0.0442 | K2: 0.0916
A3: 2 | B3: CPAP Machine - RespCare Standard | C3: Respiratory Care | D3: 279019.36 | E3: 5 | F3: 8 | G3: 34877.42 | H3: 1.6 | I3: 5580.39 | J3: 0.0213 | K3: 0.0196
A4: 3 | B4: Digital ECG Machine - VitalTrack 3-Channel | C4: Medical Equipment | D4: 226972.56 | E4: 2 | F4: 4 | G4: 56743.14 | H4: 2 | I4: 0 | J4: 0.0796 | K4: 0.0944
A5: 4 | B5: Patient Monitor - VitalTrack Multi-Parameter | C5: Medical Equipment | D5: 168893.64 | E5: 2 | F5: 4 | G5: 42223.41 | H5: 2 | I5: 0 | J5: 0.0562 | K5: 0.0887
A6: 5 | B6: Wheelchair - MobilAid Standard Folding | C6: Patient Care | D6: 158319.63 | E6: 12 | F6: 21 | G6: 7539.03 | H6: 1.75 | I6: 3166.39 | J6: 0.0023 | K6: 0.0337
A7: 6 | B7: Oxygen Concentrator 5L - ClearAir Pro | C7: Respiratory Care | D7: 153391.2 | E7: 2 | F7: 4 | G7: 38347.8 | H7: 2 | I7: 0 | J7: 0.0419 | K7: 0.0142
A8: 7 | B8: Autoclave Sterilizer 18L - CleanMed Standard | C8: Medical Equipment | D8: 129245.4 | E8: 2 | F8: 5 | G8: 25849.08 | H8: 2.5 | I8: 0 | J8: 0.0622 | K8: 0.0686
A9: 8 | B9: Stethoscope - CardioSound Classic II | C9: Stethoscopes | D9: 95556.45 | E9: 21 | F9: 29 | G9: 3295.05 | H9: 1.38 | I9: 2866.69 | J9: 0.0458 | K9: 0.0652
A10: 9 | B10: Suture Kit - PrecisionMed Absorbable (Box of 12) | C10: Surgical Instruments | D10: 90809.74 | E10: 26 | F10: 38 | G10: 2389.73 | H10: 1.46 | I10: 908.1 | J10: 0.0289 | K10: 0.0718
A11: 10 | B11: Stethoscope - CardioSound Cardiology III | C11: Stethoscopes | D11: 82848.48 | E11: 9 | F11: 11 | G11: 7531.68 | H11: 1.22 | I11: 2485.45 | J11: 0.0094 | K11: 0.0123
A12: 11 | B12: Digital BP Monitor - VitalCheck Arm Cuff | C12: Diagnostic | D12: 76715.12 | E12: 38 | F12: 46 | G12: 1667.72 | H12: 1.21 | I12: 2301.45 | J12: 0.0426 | K12: 0.0886
A13: 12 | B13: Wheelchair - MobilAid Reclining Deluxe | C13: Patient Care | D13: 75720.45 | E13: 4 | F13: 5 | G13: 15144.09 | H13: 1.25 | I13: 0 | J13: 0.0161 | K13: 0.0175
... A62: 61 | B62: Ryles Tube 14FG - FlexCare Disposable | C62: Patient Care | D62: 2379.14 | E62: 42 | F62: 47 | G62: 50.62 | H62: 1.12 | I62: 0 | J62: 0.0651 | K62: 0.0446
B63: Total | D63: =SUM(D2:D62) -> 3183211.3 | E63: =SUM(E2:E62) -> 1273 | F63: =SUM(F2:F62) -> 1751 | I63: =SUM(I2:I62) -> 37881.78
A65: Note: High-value equipment (oxygen concentrators, BiPAP/CPAP machines, patient monitors) generates strong revenue per unit but low volume, while disposables (catheters, cotton, gloves, masks) drive high volume at low value per unit - a mix consistent with the case's description of MFI's product range, from 'stethoscopes to thermometers to sutures ... CPAP and BiPAP machines' down to 'the most basic disposables, like cotton balls.'

Sheet E-Commerce Behaviour Funnel
A1: User Type | B1: All Sessions | C1: Product View | D1: Add to Cart | E1: Cart Abandonment | F1: Checkout | G1: Checkout Abandonment | H1: Successful Transaction
A2: New visitor | B2: 268400 | C2: 34900 | D2: 1980 | E2: 1470 | F2: 640 | G2: 590 | H2: 50
A3: Returning visitor | B3: 95370 | C3: 9800 | D3: 1140 | E3: 810 | F3: 480 | G3: 430 | H3: 141
A4: Total | B4: =SUM(B2:B3) -> 363770 | C4: =SUM(C2:C3) -> 44700 | D4: =SUM(D2:D3) -> 3120 | E4: =SUM(E2:E3) -> 2280 | F4: =SUM(F2:F3) -> 1120 | G4: =SUM(G2:G3) -> 1020 | H4: =SUM(H2:H3) -> 191
A6: Note: Each column is a count of sessions reaching that stage, not a strict subset of the previous column (a limitation flagged in the case: MFI's team never analysed how far customers moved through the funnel or where they dropped off). Returning visitors convert at a markedly higher rate than new visitors despite far fewer sessions - relevant evidence for a retention- or loyalty-focused pathway.

Sheet Quarterly Spend & Revenue
A1: Quarter | B1: Paid Search Spend (Rs) | C1: Social (Facebook) Spend (Rs) | D1: Email Spend (Rs) | E1: Agency Retainer (Rs) | F1: Total Spend (Rs) | G1: Total Revenue (Rs) | H1: Total Transactions
A2: 2015 Q3 (Sep only) | B2: 58667 | C2: 49333 | D2: 8000 | E2: 200000 | F2: 316000 | G2: 140000 | H2: 30
A3: 2015 Q4 | B3: 88000 | C3: 74000 | D3: 12000 | E3: 300000 | F3: 474000 | G3: 480000 | H3: 105
A4: 2016 Q1 | B4: 88000 | C4: 74000 | D4: 12000 | E4: 300000 | F4: 474000 | G4: 560000 | H4: 122
A5: 2016 Q2 | B5: 88000 | C5: 74000 | D5: 12000 | E5: 300000 | F5: 474000 | G5: 610000 | H5: 133
A6: 2016 Q3 | B6: 88000 | C6: 74000 | D6: 12000 | E6: 300000 | F6: 474000 | G6: 650000 | H6: 140
A7: 2016 Q4 | B7: 88000 | C7: 74000 | D7: 12000 | E7: 300000 | F7: 474000 | G7: 700000 | H7: 150
A8: 2017 Q1 | B8: 88000 | C8: 74000 | D8: 12000 | E8: 300000 | F8: 474000 | G8: 760000 | H8: 163
A9: 2017 Q2 | B9: 88000 | C9: 74000 | D9: 12000 | E9: 300000 | F9: 474000 | G9: 790000 | H9: 168
A10: 2017 Q3 | B10: 88000 | C10: 74000 | D10: 12000 | E10: 300000 | F10: 474000 | G10: 740000 | H10: 158
A11: 2017 Q4 | B11: 88000 | C11: 74000 | D11: 12000 | E11: 300000 | F11: 474000 | G11: 690000 | H11: 148
A12: 2018 Q1 | B12: 88000 | C12: 74000 | D12: 12000 | E12: 300000 | F12: 474000 | G12: 610000 | H12: 131
A13: 2018 Q2 | B13: 88000 | C13: 74000 | D13: 12000 | E13: 300000 | F13: 474000 | G13: 540000 | H13: 116
A14: 2018 Q3 (Jul-Aug) | B14: 58667 | C14: 49333 | D14: 8000 | E14: 200000 | F14: 316000 | G14: 320000 | H14: 68
A15: Total | B15: =SUM(B2:B14) -> 1085334 | C15: =SUM(C2:C14) -> 912666 | D15: =SUM(D2:D14) -> 148000 | E15: =SUM(E2:E14) -> 3700000 | F15: =SUM(F2:F14) -> 5846000 | G15: =SUM(G2:G14) -> 7590000 | H15: =SUM(H2:H14) -> 1632
A17: Note: Spend figures are modelled directly on the case's account of a fixed Rs 200,000/month ad budget plus a Rs 100,000/month agency retainer, with Paid Search and Facebook together consuming roughly 75% of ad spend. Revenue rises through 2016-2017 then plateaus and falls into 2018, consistent with the company closing in August 2018.

Sheet KPI Reference Sheet
A1: KPI | B1: How It Is Calculated | C1: What It Tells You
A2: Customer Acquisition Cost (CAC) | B2: Marketing spend / number of new customers acquired | C2: The cost of winning one new paying customer through a given channel
A3: Return on Ad Spend (ROAS) | B3: Revenue attributable to a channel / spend on that channel | C3: Whether paid media is generating more revenue than it costs
A4: E-Commerce Conversion Rate | B4: Transactions / sessions | C4: How effectively site traffic is converted into completed orders
A5: Average Order Value (AOV) | B5: Revenue / number of transactions | C5: The typical size of a single order, useful for spotting basket-building or upsell opportunities
A6: Bounce Rate | B6: Single-page sessions / total sessions | C6: How often visitors leave without engaging further - a proxy for landing-page or targeting relevance
A7: Cart Abandonment Rate | B7: 1 - (checkouts started / carts created) | C7: How much demand is lost between adding a product to cart and beginning checkout
A8: Customer Lifetime Value (CLV) | B8: Average order value x purchase frequency x average customer lifespan | C8: The long-run value of retaining a customer, useful for justifying retention investment
A9: Channel Contribution to Revenue | B9: Channel revenue / total revenue | C9: Which channels are actually driving the business, as distinct from which absorb the most budget
A10: Assisted Conversion Ratio | B10: Assisted conversions / last-click conversions for a channel | C10: Whether a channel plays a supporting role earlier in the customer journey rather than closing the sale

Sheet ANALYSIS
A1: Channel | B1: Sessions | C1: 3-year Ad Spend (Rs) | D1: Transactions | E1: Revenue (Rs) | F1: Spend Share | G1: Revenue Share | H1: Conversion Rate | I1: AOV | J1: CAC | K1: ROAS | L1: Rev/Visit
A2: Organic search | B2: ='Channel Performance'!C2 -> 178540 | C2: ='Channel Performance'!J2 -> 0 | D2: ='Channel Performance'!H2 -> 750 | E2: ='Channel Performance'!I2 -> 3270900 | F2: =IFERROR(C2/$C$8, 0) -> 0 | G2: =E2/$E$8 -> 0.38575118 | H2: =D2/B2 -> 0.0042007393 | I2: =E2/D2 -> 4361.2 | J2: =IF(C2=0, "-", C2/D2) -> - | K2: =IF(C2=0, "-", E2/C2) -> - | L2: =E2/B2 -> 18.320264
A3: Direct | B3: ='Channel Performance'!C3 -> 63880 | C3: ='Channel Performance'!J3 -> 0 | D3: ='Channel Performance'!H3 -> 371 | E3: ='Channel Performance'!I3 -> 1704600 | F3: =IFERROR(C3/$C$8, 0) -> 0 | G3: =E3/$E$8 -> 0.20103075 | H3: =D3/B3 -> 0.0058077646 | I3: =E3/D3 -> 4594.6092 | J3: =IF(C3=0, "-", C3/D3) -> - | K3: =IF(C3=0, "-", E3/C3) -> - | L3: =E3/B3 -> 26.684408
A4: Referral | B4: ='Channel Performance'!C4 -> 13760 | C4: ='Channel Performance'!J4 -> 0 | D4: ='Channel Performance'!H4 -> 399 | E4: ='Channel Performance'!I4 -> 2318500 | F4: =IFERROR(C4/$C$8, 0) -> 0 | G4: =E4/$E$8 -> 0.27343059 | H4: =D4/B4 -> 0.028997093 | I4: =E4/D4 -> 5810.7769 | J4: =IF(C4=0, "-", C4/D4) -> - | K4: =IF(C4=0, "-", E4/C4) -> - | L4: =E4/B4 -> 168.49564
A5: Paid search | B5: ='Channel Performance'!C5 -> 48330 | C5: ='Channel Performance'!J5 -> 3600000 | D5: ='Channel Performance'!H5 -> 150 | E5: ='Channel Performance'!I5 -> 612300 | F5: =IFERROR(C5/$C$8, 0) -> 0.5 | G5: =E5/$E$8 -> 0.07221115 | H5: =D5/B5 -> 0.0031036623 | I5: =E5/D5 -> 4082 | J5: =IF(C5=0, "-", C5/D5) -> 24000 | K5: =IF(C5=0, "-", E5/C5) -> 0.17008333 | L5: =E5/B5 -> 12.66915
A6: Social | B6: ='Channel Performance'!C6 -> 58120 | C6: ='Channel Performance'!J6 -> 3000000 | D6: ='Channel Performance'!H6 -> 128 | E6: ='Channel Performance'!I6 -> 501800 | F6: =IFERROR(C6/$C$8, 0) -> 0.41666667 | G6: =E6/$E$8 -> 0.059179413 | H6: =D6/B6 -> 0.00220234 | I6: =E6/D6 -> 3920.3125 | J6: =IF(C6=0, "-", C6/D6) -> 23437.5 | K6: =IF(C6=0, "-", E6/C6) -> 0.16726667 | L6: =E6/B6 -> 8.633861
A7: Email | B7: ='Channel Performance'!C7 -> 1140 | C7: ='Channel Performance'!J7 -> 600000 | D7: ='Channel Performance'!H7 -> 13 | E7: ='Channel Performance'!I7 -> 71200 | F7: =IFERROR(C7/$C$8, 0) -> 0.083333333 | G7: =E7/$E$8 -> 0.0083969196 | H7: =D7/B7 -> 0.011403509 | I7: =E7/D7 -> 5476.9231 | J7: =IF(C7=0, "-", C7/D7) -> 46153.846 | K7: =IF(C7=0, "-", E7/C7) -> 0.11866667 | L7: =E7/B7 -> 62.45614
A8: Total | B8: ='Channel Performance'!C8 -> 363770 | C8: ='Channel Performance'!J8 -> 7200000 | D8: ='Channel Performance'!H8 -> 1811 | E8: ='Channel Performance'!I8 -> 8479300 | F8: =SUM(F2:F7) -> 1 | G8: =SUM(G2:G7) -> 1 | H8: =D8/B8 -> 0.0049784204 | I8: =E8/D8 -> 4682.1093 | J8: =C8/(D5+D6+D7) -> 24742.268
A10: Gross margin (assumption) | B10: 25%
A11: Gross profit | B11: =E8*B10 -> 2119825
A12: Total marketing incl. retainer | B12: =200000*36+100000*36 -> 10800000
A13: Revenue per ₹1 of marketing spend | B13: =E8/B12 -> 0.78512037
A14: Net contribution | B14: =B11-B12 -> -8680175
A15: Affordable monthly media budget | B15: =B11/36 -> 58884.028
A16: Overcommitment multiple | B16: =200000/B15 -> 3.3965068
A18: Source | B18: Sessions | C18: Transactions
A19: google / display | B19: ='Source Data'!D6 -> 11200 | C19: ='Source Data'!I6 -> 10
A20: instagram / cpc | B20: ='Source Data'!D9 -> 6900 | C20: ='Source Data'!I9 -> 9
A21: Combined | B21: =B19+B20 -> 18100 | C21: =C19+C20 -> 19
A23: User Type | B23: All Sessions | C23: Successful transactions | D23: Conv
A24: New visitor | B24: ='E-Commerce Behaviour Funnel'!B2 -> 268400 | C24: ='E-Commerce Behaviour Funnel'!H2 -> 50 | D24: =C24/B24 -> 0.00018628912
A25: Returning visitor | B25: ='E-Commerce Behaviour Funnel'!B3 -> 95370 | C25: ='E-Commerce Behaviour Funnel'!H3 -> 141 | D25: =C25/B25 -> 0.0014784523
A26: Multiple | D26: =D25/D24 -> 7.9363322
A28: Sensitivity block
A29: Margin | B29: Gross profit (Rs) | C29: Affordable monthly media (Rs) | D29: Overcommitment | E29: Net contribution (Rs)
A30: 0.2 | B30: =$E$8*A30 -> 1695860 | C30: =B30/36 -> 47107.222 | D30: =200000/C30 -> 4.2456335 | E30: =B30-ANALYSIS!$B$12 -> -9104140
A31: 0.25 | B31: =$E$8*A31 -> 2119825 | C31: =B31/36 -> 58884.028 | D31: =200000/C31 -> 3.3965068 | E31: =B31-ANALYSIS!$B$12 -> -8680175
A32: 0.3 | B32: =$E$8*A32 -> 2543790 | C32: =B32/36 -> 70660.833 | D32: =200000/C32 -> 2.8304223 | E32: =B32-ANALYSIS!$B$12 -> -8256210

Sheet QUARTERLY CHART
A1: Quarter | B1: Total Spend (Rs) | C1: Total Revenue (Rs)
A2: 2015 Q3 (Sep only) | B2: ='Quarterly Spend & Revenue'!F2 -> 316000 | C2: ='Quarterly Spend & Revenue'!G2 -> 140000
A3: 2015 Q4 | B3: ='Quarterly Spend & Revenue'!F3 -> 474000 | C3: ='Quarterly Spend & Revenue'!G3 -> 480000
A4: 2016 Q1 | B4: ='Quarterly Spend & Revenue'!F4 -> 474000 | C4: ='Quarterly Spend & Revenue'!G4 -> 560000
A5: 2016 Q2 | B5: ='Quarterly Spend & Revenue'!F5 -> 474000 | C5: ='Quarterly Spend & Revenue'!G5 -> 610000
A6: 2016 Q3 | B6: ='Quarterly Spend & Revenue'!F6 -> 474000 | C6: ='Quarterly Spend & Revenue'!G6 -> 650000
A7: 2016 Q4 | B7: ='Quarterly Spend & Revenue'!F7 -> 474000 | C7: ='Quarterly Spend & Revenue'!G7 -> 700000
A8: 2017 Q1 | B8: ='Quarterly Spend & Revenue'!F8 -> 474000 | C8: ='Quarterly Spend & Revenue'!G8 -> 760000
A9: 2017 Q2 | B9: ='Quarterly Spend & Revenue'!F9 -> 474000 | C9: ='Quarterly Spend & Revenue'!G9 -> 790000
A10: 2017 Q3 | B10: ='Quarterly Spend & Revenue'!F10 -> 474000 | C10: ='Quarterly Spend & Revenue'!G10 -> 740000
A11: 2017 Q4 | B11: ='Quarterly Spend & Revenue'!F11 -> 474000 | C11: ='Quarterly Spend & Revenue'!G11 -> 690000
A12: 2018 Q1 | B12: ='Quarterly Spend & Revenue'!F12 -> 474000 | C12: ='Quarterly Spend & Revenue'!G12 -> 610000
A13: 2018 Q2 | B13: ='Quarterly Spend & Revenue'!F13 -> 474000 | C13: ='Quarterly Spend & Revenue'!G13 -> 540000
A14: 2018 Q3 (Jul-Aug) | B14: ='Quarterly Spend & Revenue'!F14 -> 316000 | C14: ='Quarterly Spend & Revenue'!G14 -> 320000
A15: Total | B15: =SUM(B2:B14) -> 5846000 | C15: =SUM(C2:C14) -> 7590000

Sheet RECONCILIATION
A1: Sheet | B1: Transactions | C1: Revenue (Rs) | D1: Media Spend (Rs)
A2: Channel Performance | B2: =SUM('Channel Performance'!H2:H7) -> 1811 | C2: =SUM('Channel Performance'!I2:I7) -> 8479300 | D2: =SUM('Channel Performance'!J2:J7) -> 7200000
A3: Source Data | B3: =SUM('Source Data'!I2:I21) -> 1435 | C3: =SUM('Source Data'!J2:J21) -> 6478700 | D3: —
A4: Quarterly Spend & Revenue | B4: =SUM('Quarterly Spend & Revenue'!H2:H14) -> 1632 | C4: =SUM('Quarterly Spend & Revenue'!G2:G14) -> 7590000 | D4: =SUM('Quarterly Spend & Revenue'!B2:D14) -> 2146000
A5: Customer Demographics | B5: =SUM('Customer Demographics'!H2:H7) -> 1449 | C5: =SUM('Customer Demographics'!I2:I7) -> 6879200 | D5: —
A6: City Performance | B6: — | C6: =SUM('City Performance'!I2:I41) -> 6629973 | D6: —
A7: Regional Analysis | B7: =SUM('Regional Analysis'!H2:H10) -> 1128 | C7: =SUM('Regional Analysis'!I2:I10) -> 5686600 | D7: —
A8: Product Performance | B8: — | C8: =SUM('Product Performance'!D2:D62) -> 3183211.3 | D8: —
A9: E-Commerce Behaviour Funnel | B9: =SUM('E-Commerce Behaviour Funnel'!H2:H3) -> 191 | C9: — | D9: —
A10: Range across sheets | B10: 191 – 1,811 | C10: 3,183,211 – 8,479,300 | D10: 2,146,000 – 7,200,000 (3.4x)
A12: No two sheets agree on transactions, revenue or spend. The analysis uses the Channel Performance base throughout.

Sheet KPI DASHBOARD
A1: KPI | B1: How it is calculated | C1: Current | D1: Target | E1: Better | F1: Status | G1: Review
A2: Tier 1 - OUTCOME (monthly, founder level)
A3: Marketing net contribution (Rs) | B3: Gross profit (revenue × margin) less all marketing cost, including the agency retainer | C3: =ANALYSIS!B14 -> -8680175 | D3: 0 | E3: High | F3: =IF(NOT(ISNUMBER(C3)),"Not yet tracked",IF(TRIM(E3)="High",IF(C3>=D3,"On target","OFF TARGET"),IF(C3<=D3,"On target","OFF TARGET"))) -> OFF TARGET | G3: Monthly
A4: Revenue per Rs 1 of marketing spend | B4: Total revenue ÷ total marketing investment; below 1.00 means marketing costs more than it earns | C4: =ANALYSIS!B13 -> 0.78512037 | D4: 4 | E4: High | F4: =IF(NOT(ISNUMBER(C4)),"Not yet tracked",IF(TRIM(E4)="High",IF(C4>=D4,"On target","OFF TARGET"),IF(C4<=D4,"On target","OFF TARGET"))) -> OFF TARGET | G4: Monthly
A5: Blended ROAS, paid channels | B5: Paid-channel revenue ÷ paid media spend; must exceed 1 ÷ gross margin simply to break even | C5: =(ANALYSIS!E5+ANALYSIS!E6+ANALYSIS!E7)/ANALYSIS!C8 -> 0.164625 | D5: 4 | E5: High | F5: =IF(NOT(ISNUMBER(C5)),"Not yet tracked",IF(TRIM(E5)="High",IF(C5>=D5,"On target","OFF TARGET"),IF(C5<=D5,"On target","OFF TARGET"))) -> OFF TARGET | G5: Monthly
A6: CAC-to-AOV ratio | B6: Customer acquisition cost ÷ average order value; above 1.00 means a first order never repays the cost of winning it | C6: =ANALYSIS!J8/ANALYSIS!I8 -> 5.2844277 | D6: 0.3 | E6: Low | F6: =IF(NOT(ISNUMBER(C6)),"Not yet tracked",IF(TRIM(E6)="High",IF(C6>=D6,"On target","OFF TARGET"),IF(C6<=D6,"On target","OFF TARGET"))) -> OFF TARGET | G6: Monthly
A7: Media spend vs affordable budget | B7: Committed monthly media budget ÷ monthly gross profit; above 1.00 means spending faster than the business generates | C7: =200000/ANALYSIS!B15 -> 3.3965068 | D7: 1 | E7: Low | F7: =IF(NOT(ISNUMBER(C7)),"Not yet tracked",IF(TRIM(E7)="High",IF(C7>=D7,"On target","OFF TARGET"),IF(C7<=D7,"On target","OFF TARGET"))) -> OFF TARGET | G7: Monthly
A8: Tier 2 - CHANNEL (monthly, trigger allocation)
A9: Referral share of revenue | B9: Referral revenue ÷ total revenue; tracks whether the partnership programme is displacing paid acquisition | C9: =ANALYSIS!G4 -> 0.27343059 | D9: 0.4 | E9: High | F9: =IF(NOT(ISNUMBER(C9)),"Not yet tracked",IF(TRIM(E9)="High",IF(C9>=D9,"On target","OFF TARGET"),IF(C9<=D9,"On target","OFF TARGET"))) -> OFF TARGET | G9: Monthly
A10: Misallocation index, paid search | B10: Share of revenue ÷ share of media spend; below 1.00 means the channel is over-funded relative to what it returns | C10: =ANALYSIS!G5/ANALYSIS!F5 -> 0.1444223 | D10: 1 | E10: High | F10: =IF(NOT(ISNUMBER(C10)),"Not yet tracked",IF(TRIM(E10)="High",IF(C10>=D10,"On target","OFF TARGET"),IF(C10<=D10,"On target","OFF TARGET"))) -> OFF TARGET | G10: Monthly
A11: Revenue per session, paid search (Rs) | B11: Paid search revenue ÷ paid search sessions; measures the quality of bought traffic rather than its volume | C11: =ANALYSIS!L5 -> 12.66915 | D11: 50 | E11: High | F11: =IF(NOT(ISNUMBER(C11)),"Not yet tracked",IF(TRIM(E11)="High",IF(C11>=D11,"On target","OFF TARGET"),IF(C11<=D11,"On target","OFF TARGET"))) -> OFF TARGET | G11: Monthly
A12: Revenue per partner per month (Rs) | B12: Revenue attributable to each referral partner; the basis for scaling or dropping individual pilots | C12: n/a — new programme | D12: 60000 | E12: High | F12: =IF(NOT(ISNUMBER(C12)),"Not yet tracked",IF(TRIM(E12)="High",IF(C12>=D12,"On target","OFF TARGET"),IF(C12<=D12,"On target","OFF TARGET"))) -> Not yet tracked | G12: Monthly
A13: Tier 3 - LEADING INDICATORS (weekly)
A14: Returning-visitor share of orders | B14: Orders from returning visitors ÷ all orders; the primary test of whether retention activity is working | C14: =ANALYSIS!C25/(ANALYSIS!C24+ANALYSIS!C25) -> 0.7382199 | D14: 0.8 | E14: High | F14: =IF(NOT(ISNUMBER(C14)),"Not yet tracked",IF(TRIM(E14)="High",IF(C14>=D14,"On target","OFF TARGET"),IF(C14<=D14,"On target","OFF TARGET"))) -> OFF TARGET | G14: Weekly
A15: Returning conversion multiple | B15: Returning-visitor conversion rate ÷ new-visitor conversion rate; confirms the retention opportunity persists as the base grows | C15: =ANALYSIS!D26 -> 7.9363322 | D15: 5 | E15: High | F15: =IF(NOT(ISNUMBER(C15)),"Not yet tracked",IF(TRIM(E15)="High",IF(C15>=D15,"On target","OFF TARGET"),IF(C15<=D15,"On target","OFF TARGET"))) -> On target | G15: Weekly
A16: Site conversion rate | B16: Transactions ÷ sessions across all channels; the headline measure of site effectiveness | C16: =ANALYSIS!H8 -> 0.0049784204 | D16: 0.01 | E16: High | F16: =IF(NOT(ISNUMBER(C16)),"Not yet tracked",IF(TRIM(E16)="High",IF(C16>=D16,"On target","OFF TARGET"),IF(C16<=D16,"On target","OFF TARGET"))) -> OFF TARGET | G16: Weekly
A17: Engaged email list size | B17: First-party contacts who opened or clicked within 90 days; the asset all email revenue depends on | C17: n/a — not tracked | D17: 2000 | E17: High | F17: =IF(NOT(ISNUMBER(C17)),"Not yet tracked",IF(TRIM(E17)="High",IF(C17>=D17,"On target","OFF TARGET"),IF(C17<=D17,"On target","OFF TARGET"))) -> Not yet tracked | G17: Weekly
A18: Tier 4 - DATA QUALITY (monthly)
A19: Revenue variance between reports | B19: Gap between channel-level and quarterly revenue ÷ channel-level revenue; measures whether reporting can be relied on at all | C19: =(RECONCILIATION!C2-RECONCILIATION!C4)/RECONCILIATION!C2 -> 0.10487894 | D19: 0.02 | E19: Low | F19: =IF(NOT(ISNUMBER(C19)),"Not yet tracked",IF(TRIM(E19)="High",IF(C19>=D19,"On target","OFF TARGET"),IF(C19<=D19,"On target","OFF TARGET"))) -> OFF TARGET | G19: Monthly
A20: Sessions with no identified source | B20: Sessions with no named source ÷ all sessions; untracked traffic can be neither funded nor cut | C20: =('Channel Performance'!C8-'Source Data'!D22)/'Channel Performance'!C8 -> 0.066690491 | D20: 0.02 | E20: Low | F20: =IF(NOT(ISNUMBER(C20)),"Not yet tracked",IF(TRIM(E20)="High",IF(C20>=D20,"On target","OFF TARGET"),IF(C20<=D20,"On target","OFF TARGET"))) -> OFF TARGET | G20: Monthly
A21: Revenue with no identified source | B21: Revenue not attributable to any named source ÷ total revenue; a channel that cannot be identified cannot be funded or cut | C21: =(RECONCILIATION!C2-RECONCILIATION!C3)/RECONCILIATION!C2 -> 0.23593929 | D21: 0.02 | E21: Low | F21: =IF(NOT(ISNUMBER(C21)),"Not yet tracked",IF(TRIM(E21)="High",IF(C21>=D21,"On target","OFF TARGET"),IF(C21<=D21,"On target","OFF TARGET"))) -> OFF TARGET | G21: Monthly
A22: Product pages with working tracking | B22: Product pages correctly linked to revenue tracking ÷ all product pages; the case states many were never connected | C22: n/a — not measured | D22: 1 | E22: High | F22: =IF(NOT(ISNUMBER(C22)),"Not yet tracked",IF(TRIM(E22)="High",IF(C22>=D22,"On target","OFF TARGET"),IF(C22<=D22,"On target","OFF TARGET"))) -> Not yet tracked | G22: Monthly
A23: Days from month-end to reporting | B23: Working days from month-end until the report is available; slow reporting makes timely reallocation impossible | C23: n/a — not measured | D23: 5 | E23: Low | F23: =IF(NOT(ISNUMBER(C23)),"Not yet tracked",IF(TRIM(E23)="High",IF(C23>=D23,"On target","OFF TARGET"),IF(C23<=D23,"On target","OFF TARGET"))) -> Not yet tracked | G23: Monthly
A25: Weekly channel review · Monthly reallocation decision with authority to move budget · Quarterly zero-based rebuild. Any Tier 2 metric below 0.50 is automatically tabled for reduction.
